{
  "#3E1C583D": "Notice",
  "#3E05D48A": "Guest Login",
  "#210F53E": "Confirm",
  "#1285DD": "Account",
  "#AD336": "News",
  "#B97DC": "Video",
  "#C36EF": "Support",
  "#5A91AD27": "Welcome! {0}",
  "#504B1BE7": "Start Game",
  "#4022A5DA": "{0} - Unlinked",
  "#50DB063F": "{0} - Linked",
  "#5065CE57": "Logout",
  "#D570A": "Notification",
  "#1011D2": "OK",
  "#DD6D659A": "Connection lost. Please relogin.",
  "#77990508": "Select Server",
  "#551CD46E": "Recommended\nServer",
  "#3153760B": "My Servers",
  "#1C15B76": " Server",
  "#E8AA6": "Free",
  "#10A63A": "Crowded",
  "#EEFD1": "Full",
  "#10C018": "Offline",
  "#D5BF8": "New!",
  "#10E901": "Eyes",
  "#16A2585": "Novice",
  "#10C51F": "Hairstyle",
  "#C9C00": "Choose",
  "#35A111C6": "Start\nAdventure",
  "#4B2A6F12": "<color=$$Yellow$$>Highest Level</color>",
  "#98E98475": "Are you sure you want to delete the {0} character from your list?\n(Delete is irreversible once countdown is done.)",
  "#C12DFC97": "Disconnected from the server. Retry?",
  "#52591F05": "Retry",
  "#5BBBEF52": "Back to Login",
  "#B3C1E": "Cancel",
  "#FE1C8": "OK",
  "#183D1": "YES",
  "#F8D3E3B3": "Characters under Lv.<color=$$Yellow$$>{0}</color> can be deleted <color=$$Yellow$$>immediately</color> without waiting. Please enter '{1}' at the bottom to delete.",
  "#77E50164": "Reconnecting",
  "#1C35B9": "2.5D",
  "#25507B": "Base",
  "#1453B": "Job",
  "#8CEAEC7": "Ch.{0}",

  "hairstyle": "",
  "#1923AFF": "Mushroom",
  "#1ED278F": "Flame",
  "#53C60C5C": "Short Bangs",
  "#3DCCB6FC": "Cool",
  "#23EC953": "Swag",
  "#DB7F9": "Palm",
  "#141942": "Storm",
  "#449DDAC8": "Emo",
  "#1943F19": "Student",

  "#48440E88": "Innocent",
  "#2C6F5A45": "Short",
  "#19636EC": "Ribbon",
  "#426AAF3A": "Cute",
  "#359B1B05": "Alp Hair",
  "#164C40E": "Princess",
  "#AC8DD": "Elegant",
  "#1943F19": "Student",
  "#1941490": "Straight",

  "eyes": "",
  "#2674208": "Smart",
  "#306C7026": "Rebel",
  "#16A6FCF": "Cold",
  "#29DBAA7": "Young",
  "#4FC55561": "Cool",
  "#1E22D12": "Calm",
  "#306C6B25": "Confident",
  "#2F06F948": "Cold",
  "#36A777E7": "Young",
  "#4872A545": "Fierce",

  "-- gui buttons --": "",
  "#16B5D3A": "Auto Atk",
  "#10ED51": "Bag",
  "#B1550": "RO Shop",
  "#A8937": "Shop",
  "#BD6C7": "Gift",
  "#CFD37": "Diary",
  "#D337D": "Skill",
  "#E9D49E9": "Open{1} at <color=#fff94b>Lv.{0}</color>",
  "#B31C8": "Card",
  "#E6743": "Event",
  "#BF6AC": "Daily Quest",
  "#12241A": "Watch",
  "#495065AA": "Special Event",
  "#122B94": "Pick",


  "--Diary--":"",
  "#6A5A8920": "Click the Book to view its content.",
  "#2F484330": "Journal",
  "#4C860E9E": "Equipment",
  "#571F44AF": "Monsters",
  "#182F2023": "Poring Notes",
  "#2FAA8CFA": "Cards",
  "#BC964FB9": "Customization",
  "#2F479232": "Return",


  "-- notifications --": "",
  "#95FA72B3": "Check Freya's Luck charm!",
  "#AB8B7A13": "Idle",
  "#45EA0A6C": "Unlocked at Base Lv.{0}",
  "#263717D": "Please wait.",
  "#806FE1F8": "Limit has been reached. Try again tomorrow.",


  "--battle time--": "--battle time--",
  "#DFCE6946": "Offline Bonus",
  "#83F52A5A": "Yesterday's Battle Time {0}\nis now converted into Offline Bonus!",
  "#443D4204": "<color=$$Blue$$>Base</color> offline bonus: {0}",
  "#15E0E98": "<color=$$Yellow$$>Job</color> offline bonus: {0}",
  "#574D804": "Offline bonus is only available once per day. Come and explore the world!",
  "#34F61A88": "Battle Time",
  "#B2765": " mins",
  "#ABBBC": "Good",
  "#5C32ED45": "Daily Offline Bonus",
  "#449760D2": " BONUS",
  "#70B9": "pt.",
  "#25507B": "Base",
  "#1497B": "Job",
  "#80AC4F50": "Return to city between 4:45-4:55AM before reset.",
  "#558778BB": "Recommended\nHunting Ground",
  "#ECDC7E4D": "If the experience gained through battles on the previous day is small, or if a daily quests remains, it can be converted into Offline Bonus the next day.",
  "#2D219DE4": "1. Maximum daily Battle Stamina is 120 points. If you reached the daily battle stamina, you will not gain Exp and Drop.\n2. You can activate Freya's Luck to get items from the monster while your Battle Stamins is exhausted.\n3. Battle stamina will not be consumed while using Freya's Luck.",
  "#5B8A1198": "Level:",
  "#44C3828B": "GO",
  "#14C6F631": "Reason:{0}",
  "#55FFF7EF": "Recommended Monsters:",
  "#54DA9200": "Map:",
  "#C1447871": "They are all very dense as persistent monsters. Hunting efficiency is very good if you use the fire attribute range skill, but it is rather dangerous. It is recommended to go to the party.",


  "-- auto attack --": "",
  "#2F209B8D": "All Monsters",
  "#48A9D901": "Auto Battle:",
  "#2ECA0D99": "Setting",
  "#3A099F66": "Mode:",
  "#3A726D4D": "Radius:",
  "#42DA73EA": "Auto Potion",
  "#F426C873": "Auto Battle at Quest",

  "-- Maps --":"",
  "#2E0BF745": "Orc Village",

  "--mail & friends--": "",
  "#13FD1C": "Receive",
  "#463EF063": "Item List:",
  "#12F564": "Mail",
  "#BDCE8": "Friends",
  "#3AEFB1C4": "Recent Chats",
  "#3281D447": "Friend List",
  "#7DB033": "Choose a friend from the list.",
  "#F3B8857B": "Kafra Employee",
  "#AB5A455C": "Ask me anything!",
  "#DA7849A5": "Need anything? Tips? Game Support? Ask me anything!",
  "#48AAC2FA": "Inquire",
  "#D3B4E409": "No friends. Add friend now.",
  "#2D5423CA": "Receive All",
  "#2D4B5332": "Delete All",
  "#B2C84": "Delete",
  "#49F43056": "No mail...",
  "#39F78C6D": "No Title",
  "#3A9BD330": "Friend",
  "#28EC105": "Stranger",
  "#3304090D": "Do you want to delete your chat history with {0}?",
  "#CF21EEA": "Start chatting..",
  "#B5DF2": "Send",
  "#431E6A9D": "Under development...",
  "#3DBA47A3": "Add Friend",
  "#A2C108CE": "Enter Name or ID...",
  "#D64BE": "Search",
  "#10DBE824": "Search friend by Name or ID",
  "#3650DBF5": "Pin Chat",
  "#7060FA16": "Chat pinned complete!",
  "#A8622": "World",
  "#C7697": "System",


  "-- player information --": "",
  "#10D7E6": "Job",
  "#1C169C7": "No Title",
  "#8A87244": "Basic Stats",
  "#226E801": "Stats",
  "#DD356984": "Bonus",
  "#38717E89": "Pts.",  
  "#88B55B3D": "Preset 1",
  "#88B55B46": "Preset 3",
  "#88B55BC9": "Preset 2",
  "#26C40C03": "STR",
  "#5FCC5B17": "AGI",
  "#E8D698CE": "VIT",
  "#6BB06960": "INT",
  "#267CBA3D": "DEX",
  "#FC586B14": "LUK",
  "#2E911CAB": "Points:",
  "#38DF5151": "Allocate",
  "#124684": "Player",
  "#12FD38": "Job",
  "#3E017C4B": "Job Advancement Tree",
  "#50D233E8": "Bonus Stats",
  "#503B5020": "High Wizard",
  "#3A9AA2B8": "Basic Info.",
  "#4EDCBEDC": "More Info.",
  "#51037947": "Basic",
  "#570FD884": "Advance",
  "#409B4A28": "Special",
  "#4655E07E": "Refine ATK",  
  "#46561175": "Refine DEF",
  "#465B26C9": "Refine MATK",
  "#465B57C0": "Refine MDEF",
  "#41AC4827": "HP Recovery",
  "#57074C94": "SP Recovery",
  "#2F765897": "Variable CT",
  "#31428404": "Fixed CT",
  "#F1C5A6FB": "Inc. Heal",
  "#43274A62": "Phy. Dmg",
  "#2797F0CD": "Magic Dmg",
  "#16809FC3": "Ignore DEF",
  "#C972C853": "Melee Dmg",
  "#44560B68": "Movement Spd",
  "#1E416B9C": "Variable CT%",
  "#599304A9": "Fixed CT%",
  "#8376F932": "Heal Receive",
  "#4321A82E": "Phy. Dmg Reduc",
  "#27924E99": "Magic Dmg Reduc",
  "#172EAF6E": "Ignore MDEF",
  "#F5AF6C71": "Range Dmg",


  "-- quests --": "",
  "#A80FC": "Main",
  "#F559E": "Side",
  "#C126E": "Adv.",
  "#AFE8D85D": "Completion Reward:",
  "#D6C01": "Abandon",
  "#AFB6D": "Go",
  "#2EC4B6C8": "Accept",

  "--classes--": "--classes--",
  "#C7953": "Wizard",


  "--wizard-skills--": "--wizard-skills--",



  "-- monster book gui --": "",
  "#5725E4E8": "Monster\nDetail",
  "#38C90709": "Research\nDetail",
  "#43F3C8F5": "Research Detail",
  "#542444D0": "Enter keyword..",
  "#16B151F": "Basic Stat",
  "#4EDE5AB1": "Detailed Stat",

  "#AF6C3": "Property",
  "#65E0": "Neutral",
  "#98CE": "Wind",
  "#5730": "Earth",
  "#706B": "Fire",
  "#6C34": "Water",
  "#6BD2": "Poison",
  "#5723": "Holy",
  "#6697": "Shadow",
  "#5FF5": "Ghost",
  "#A7B28": "Undead",

  "#10193C": "Race",
  "#B1A11": "Brute",
  "#A855C": "Demi-Human",
  "#D0A8A": "Demon",
  "#DFD16": "Formless",
  "#DAD31": "Insect",
  "#14B919": "Fish",
  "#D8142": "Formless",
  "#BCDC8": "Angel",
  "#14F888": "Dragon",

  "#A913E": "Size",
  "#C357A": "Small",
  "#A6B58": "Medium",
  "#BD592": "Large",

  "#106366": "Type",
  "#3AA46E85": "Normal Monster",


  "#38D3045": "Exp Rate:",
  "#86F89423": "Loot Rate:",
  "#F21C0": "Characteristic",
  "#D58E6": "Loots",
  "#BADE9": "Pointers",

  "#717933C8": "Level Penalty Chart",
  "#2B88A49B": "Monster <color=#37904e>HIGHER</color> than your current level.",
  "#49EE948B": "Monster <color=#dc734a>LOWER</color> than your current level.",
  "#21D22FE": "Level\nDifference",
  "#482830BB": "Exp Rate",
  "#3A6497E9": "Drop Rate",


  "#326DBF08": "<a href=MarkTips@@ATTR_TIPS_ANIMAL_RACE>Brute</a>",
  "#2BB1A2CF": "<a href=MarkTips@@ATTR_TIPS_SHAPELESS_RACE>Formless</a>",
  "#E14EAD4": "<a href=MarkTips@@ATTR_TIPS_ANGEL_RACE>Angel</a>",
  "#B5E0429A": "<a href=MarkTips@@ATTR_TIPS_HUMAN_RACE>Demi\nHuman</a>",
  "#D601C39A": "<a href=MarkTips@@ATTR_TIPS_PLANT_RACE>Formless</a>",
  "#326DBF08": "<a href=MarkTips@@ATTR_TIPS_ANIMAL_RACE>Brute</a>",
  "#8BC6BF3C": "<a href=MarkTips@@ATTR_TIPS_INSECT_RACE>Insect</a>",
  "#83927220": "<a href=MarkTips@@ATTR_TIPS_FISHSHELL_RACE>Fish</a>",
  "#853567A8": "<a href=MarkTips@@ATTR_TIPS_DRAGON_RACE>Dragon</a>",
  "#3AEA5E83": "<a href=MarkTips@@ATTR_TIPS_DEVIL_RACE>Demon</a>",

  "#D0BA3DB3": "<a href=MarkTips@@ATTR_TIPS_WIND_DEFENCE_ATTR>Wind</a>",
  "#185BD9A4": "<a href=MarkTips@@ATTR_TIPS_FIRE_DEFENCE_ATTR>Fire</a>",
  "#2CC1B7CA": "<a href=MarkTips@@ATTR_TIPS_WATER_DEFENCE_ATTR>Water</a>",
  "#58543CC2": "<a href=MarkTips@@ATTR_TIPS_NILL_DEFENCE_ATTR>Neutral</a>",
  "#E8847582": "<a href=MarkTips@@ATTR_TIPS_LAND_DEFENCE_ATTR>Earth</a>",
  "#6D8C238C": "<a href=MarkTips@@ATTR_TIPS_DARK_DEFENCE_ATTR>Shadow</a>",
  "#77E975B2": "<a href=MarkTips@@ATTR_TIPS_HOLY_DEFENCE_ATTR>Holy</a>",
  "#952F2FBD": "<a href=MarkTips@@ATTR_TIPS_POISON_DEFENCE_ATTR>Poison</a>",
  "#23B4DC0": "<a href=MarkTips@@ATTR_TIPS_IMMORTAL_DEFENCE_ATTR>Undead</a>",
  "#25CBAE4B": "<a href=MarkTips@@ATTR_TIPS_THOUGHT_DEFENCE_ATTR>Ghost</a>",

  "#93D074C3": "<a href=MarkTips@@ATTR_TIPS_SMALL_SHAPE>Small</a>",
  "#F35DFF7": "<a href=MarkTips@@ATTR_TIPS_MIDDLE_SHAPE>Medium</a>",
  "#6A085774": "<a href=MarkTips@@ATTR_TIPS_BIG_SHAPE>Large</a>",

  "-- monster info --": "",
  "#1B974C0": "Loots:",
  "#4EBBE70F": "<color=$$Blue$$>Exp Rate:</color>{0} <color=$$Blue$$>Loot Rate:</color>{1}\n",

  "-- monsters --": "",
  "#E5B4B": "Poring",
  "#F7CE3": "Lunatic",
  "#11DAC4": "Pupa",
  "#3266B7C5": "Peco Peco Egg",
  "#22A4313": "Fabre",
  "#C7C10": "Picky",
  "#4B70F4AE": "Picky",
  "#1163B4": "Chonchon",
  "#DE6EF": "Willow",
  "#105093": "Condor",
  "#19ADA87": "Savage Babe",
  "#11F8A2": "Rocker",
  "#230BF6E": "Roda Frog",
  "#DF723": "Wormtail",
  "#38E658E3": "Vocal",
  "#11DC52": "Ambernite",
  "#14899B": "Spore",







  "#90DD66D9": "[Translated by: XKROMUI]\n© Gravity Co,.Ltd & Lee MyoungJin(studio DTDS). All Rights Reserved."
}